mlmbench/__init__.py
mlmbench/data.py
mlmbench/iodata.py
mlmbench/mkextgroupsplits.py
mlmbench/mkrndsplits.py
mlmbench/mktgtextrapsplits.py
mlmbench/test.py
mlmbench/data/BACE-moleculenet/Readme.md
mlmbench/data/BACE-moleculenet/cv.splits
mlmbench/data/BACE-moleculenet/dataset.csv
mlmbench/data/BACE-moleculenet/dataset.smi
mlmbench/data/BACE-moleculenet/target.csv
mlmbench/data/BACE-random/Readme.md
mlmbench/data/BACE-random/cv.splits
mlmbench/data/BACE-random/dataset.csv
mlmbench/data/BACE-random/dataset.smi
mlmbench/data/BACE-random/target.csv
mlmbench/data/BACE-tgt_extrapolation/Readme.md
mlmbench/data/BACE-tgt_extrapolation/cv.splits
mlmbench/data/BACE-tgt_extrapolation/dataset.csv
mlmbench/data/BACE-tgt_extrapolation/dataset.smi
mlmbench/data/BACE-tgt_extrapolation/target.csv
mlmbench/data/FU-random/Readme.md
mlmbench/data/FU-random/cv.splits
mlmbench/data/FU-random/dataset.csv
mlmbench/data/FU-random/dataset.smi
mlmbench/data/FU-random/target.csv
mlmbench/data/FU-tgt_extrapolation/Readme.md
mlmbench/data/FU-tgt_extrapolation/cv.splits
mlmbench/data/FU-tgt_extrapolation/dataset.csv
mlmbench/data/FU-tgt_extrapolation/dataset.smi
mlmbench/data/FU-tgt_extrapolation/target.csv
mlmbench/data/HLMCLint-random/Readme.md
mlmbench/data/HLMCLint-random/cv.splits
mlmbench/data/HLMCLint-random/dataset.csv
mlmbench/data/HLMCLint-random/dataset.smi
mlmbench/data/HLMCLint-random/target.csv
mlmbench/data/HLMCLint-tgt_extrapolation/Readme.md
mlmbench/data/HLMCLint-tgt_extrapolation/cv.splits
mlmbench/data/HLMCLint-tgt_extrapolation/dataset.csv
mlmbench/data/HLMCLint-tgt_extrapolation/dataset.smi
mlmbench/data/HLMCLint-tgt_extrapolation/target.csv
mlmbench/data/MeltingPoint-random/Readme.md
mlmbench/data/MeltingPoint-random/cv.splits
mlmbench/data/MeltingPoint-random/dataset.csv
mlmbench/data/MeltingPoint-random/dataset.smi
mlmbench/data/MeltingPoint-random/target.csv
mlmbench/data/MeltingPoint-tgt_extrapolation/Readme.md
mlmbench/data/MeltingPoint-tgt_extrapolation/cv.splits
mlmbench-1.0.3.dist-info/LICENSE
mlmbench-1.0.3.dist-info/METADATA
mlmbench-1.0.3.dist-info/WHEEL
mlmbench-1.0.3.dist-info/top_level.txt
mlmbench-1.0.3.dist-info/RECORD
