Metadata-Version: 2.1
Name: mlmbench
Version: 1.0.3
Summary: MLM MachineLearning Molecular Benchmarch
Home-page: https://github.com/gmrandazzo/mlmbench
Author: Giuseppe Marco Randazzo
Author-email: gmrandazzo@gmail.com
License: GPLv3
Requires-Python: >=3.0
License-File: LICENSE
